hypixel.py
leveling.py
hypixel-0.8.0.dist-info/LICENSE
hypixel-0.8.0.dist-info/METADATA
hypixel-0.8.0.dist-info/WHEEL
hypixel-0.8.0.dist-info/top_level.txt
hypixel-0.8.0.dist-info/RECORD
