Metadata-Version: 2.1
Name: hypixel
Version: 0.8.0
Summary: This is a simple, unofficial library for getting values from the public Hypixel-API in Python.
Home-page: https://gitlab.com/Snuggie/hypixel.py
Author: Snuggle
Author-email: snuggle@sprinkly.net
License: UNKNOWN
Keywords: hypixel hypixel-api hypixel.py
Platform: UNKNOWN
Classifier: Development Status :: 4 - Beta
Classifier: Natural Language :: English
Classifier: Operating System :: OS Independent
Classifier: Programming Language :: Python :: 3.4
Classifier: Programming Language :: Python :: 3.6
Classifier: Programming Language :: Python :: 3.7
Classifier: Topic :: Games/Entertainment
Classifier: Topic :: Software Development :: Libraries
Classifier: Topic :: Software Development :: Libraries :: Python Modules
Classifier: Topic :: Utilities
Requires-Python: >=3.3
